quicksamplemule.py
quicksamplemule-0.0.2.dist-info/LICENSE
quicksamplemule-0.0.2.dist-info/METADATA
quicksamplemule-0.0.2.dist-info/WHEEL
quicksamplemule-0.0.2.dist-info/top_level.txt
quicksamplemule-0.0.2.dist-info/RECORD
