Metadata-Version: 2.1
Name: quicksamplemule
Version: 0.0.2
Summary: Quicksample Test Package for Demo
Author: Muluken Bogale
Classifier: Programming Language :: Python :: 3
Classifier: License :: OSI Approved :: MIT License
Classifier: Operating System :: OS Independent
Requires-Python: >=3.6
License-File: LICENSE
